rm_gallery/__init__.py
rm_gallery/core/__init__.py
rm_gallery/core/base.py
rm_gallery/core/data/__init__.py
rm_gallery/core/data/annotation/__init__.py
rm_gallery/core/data/annotation/annotation.py
rm_gallery/core/data/annotation/client.py
rm_gallery/core/data/annotation/server.py
rm_gallery/core/data/annotation/template.py
rm_gallery/core/data/base.py
rm_gallery/core/data/build.py
rm_gallery/core/data/export.py
rm_gallery/core/data/load/__init__.py
rm_gallery/core/data/load/base.py
rm_gallery/core/data/load/chat_message.py
rm_gallery/core/data/load/huggingface.py
rm_gallery/core/data/process/__init__.py
rm_gallery/core/data/process/ops/__init__.py
rm_gallery/core/data/process/ops/base.py
rm_gallery/core/data/process/ops/filter/__init__.py
rm_gallery/core/data/process/ops/filter/conversation_turn_filter.py
rm_gallery/core/data/process/ops/filter/text_length_filter.py
rm_gallery/core/data/process/process.py
rm_gallery/core/data/schema.py
rm_gallery/core/model/__init__.py
rm_gallery/core/model/base.py
rm_gallery/core/model/huggingface_llm.py
rm_gallery/core/model/message.py
rm_gallery/core/model/openai_llm.py
rm_gallery/core/reward/README.md
rm_gallery/core/reward/__init__.py
rm_gallery/core/reward/base.py
rm_gallery/core/reward/composition.py
rm_gallery/core/reward/evaluator.py
rm_gallery/core/reward/refinement.py
rm_gallery/core/reward/registry.py
rm_gallery/core/reward/rubric/analyzer.py
rm_gallery/core/reward/rubric/base.py
rm_gallery/core/reward/rubric/generator.py
rm_gallery/core/reward/rubric/mcr_selector.py
rm_gallery/core/reward/rubric/structurer.py
rm_gallery/core/reward/schema.py
rm_gallery/core/reward/template.py
rm_gallery/core/train/__init__.py
rm_gallery/core/train/dataset.py
rm_gallery/core/utils/__init__.py
rm_gallery/core/utils/acc.py
rm_gallery/core/utils/file.py
rm_gallery/core/utils/logger.py
rm_gallery/core/utils/text.py
rm_gallery/core/utils/tokenizer.py
rm_gallery/gallery/__init__.py
rm_gallery/gallery/data/__init__.py
rm_gallery-0.1.7.dist-info/METADATA
rm_gallery-0.1.7.dist-info/WHEEL
rm_gallery-0.1.7.dist-info/licenses/LICENSE
rm_gallery-0.1.7.dist-info/RECORD
