Metadata-Version: 2.4
Name: rm-gallery
Version: 0.1.7
Summary: 
License-File: LICENSE
Author: Haoran Chen
Author-email: chenhaoran.chr@alibaba-inc.com
Requires-Python: >=3.10,<3.13
Classifier: Programming Language :: Python :: 3
Classifier: Programming Language :: Python :: 3.10
Classifier: Programming Language :: Python :: 3.11
Classifier: Programming Language :: Python :: 3.12
Requires-Dist: bitsandbytes (>=0.46.1)
Requires-Dist: fire
Requires-Dist: jsonlines (>=4.0.0,<5.0.0)
Requires-Dist: label-studio (>=1.17.0)
Requires-Dist: loguru (>=0.7.3,<0.8.0)
Requires-Dist: math-verify (>=0.7.0,<0.8.0)
Requires-Dist: openai (>=1.85.0,<2.0.0)
Requires-Dist: pandas (>=2.2.3,<3.0.0)
Requires-Dist: py-data-juicer (>=1.3.3)
Requires-Dist: pydantic (>=2.11.5,<3.0.0)
Requires-Dist: pytest (>=8.3.5,<9.0.0)
Requires-Dist: pytest-asyncio (>=1.1.0,<2.0.0)
Requires-Dist: pyyaml (>=6.0.2,<7.0.0)
Requires-Dist: retry (>=0.9.2,<0.10.0)
Requires-Dist: tabulate
Requires-Dist: transformers (>=4.52.4,<5.0.0)
